query_builder/__init__.py
query_builder/postgres.py
svknd_query_builder-0.1.0.dist-info/LICENSE
svknd_query_builder-0.1.0.dist-info/METADATA
svknd_query_builder-0.1.0.dist-info/WHEEL
svknd_query_builder-0.1.0.dist-info/top_level.txt
svknd_query_builder-0.1.0.dist-info/RECORD
